vienna/__init__.py
vienna/vienna.py
vienna-0.8.0.dist-info/licenses/AUTHORS.rst
vienna-0.8.0.dist-info/licenses/LICENSE
vienna-0.8.0.dist-info/METADATA
vienna-0.8.0.dist-info/WHEEL
vienna-0.8.0.dist-info/top_level.txt
vienna-0.8.0.dist-info/RECORD
