Metadata-Version: 2.4
Name: vienna
Version: 0.8.0
Summary: A short Python wrapper for Vienna tools
Author-email: Joe Yesselman <jyesselm@unl.edu>
License: MIT
Project-URL: Homepage, https://github.com/jyesselm/vienna
Project-URL: Repository, https://github.com/jyesselm/vienna
Project-URL: Issues, https://github.com/jyesselm/vienna/issues
Keywords: RNA,ViennaRNA,bioinformatics,folding
Classifier: Development Status :: 4 - Beta
Classifier: Intended Audience :: Developers
Classifier: License :: OSI Approved :: MIT License
Classifier: Natural Language :: English
Classifier: Programming Language :: Python :: 3
Classifier: Programming Language :: Python :: 3.8
Classifier: Programming Language :: Python :: 3.9
Classifier: Programming Language :: Python :: 3.10
Classifier: Programming Language :: Python :: 3.11
Classifier: Programming Language :: Python :: 3.12
Classifier: Programming Language :: Python :: Implementation :: CPython
Classifier: Programming Language :: Python :: Implementation :: PyPy
Requires-Python: >=3.8
License-File: LICENSE
License-File: AUTHORS.rst
Requires-Dist: ViennaRNA>=2.0
Requires-Dist: black
Requires-Dist: pytest
Provides-Extra: dev
Requires-Dist: black; extra == "dev"
Requires-Dist: wheel>=0.22; extra == "dev"
Requires-Dist: build; extra == "dev"
Requires-Dist: twine; extra == "dev"
Dynamic: license-file
